langchain_hcxai/__init__.py
langchain_hcxai/callbacks/__init__.py
langchain_hcxai/callbacks/callback.py
langchain_hcxai/chat_models/__init__.py
langchain_hcxai/chat_models/chat.py
langchain_hcxai/embeddings/__init__.py
langchain_hcxai/embeddings/embedding.py
langchain_hcxai/llms/__init__.py
langchain_hcxai/llms/llm.py
langchain_hcxai/py.typed
langchain_hcxai/utils/__init__.py
langchain_hcxai/utils/hcxai.py
langchain_hcxai/vectorstores/__init__.py
langchain_hcxai/vectorstores/milvus_extend.py
langchain_hcxai/vectorstores/text_splitter.py
langchain_hcxai-0.1.11.dist-info/METADATA
langchain_hcxai-0.1.11.dist-info/WHEEL
langchain_hcxai-0.1.11.dist-info/RECORD
