Metadata-Version: 2.1
Name: langchain-hcxai
Version: 0.1.11
Summary: Community contributed LangChain integrations for Naver AI.
Home-page: https://gitlab.com/didim365-ai/naver-ai
License: Copyright (c) Didim365.com
Author: HCX Support
Author-email: ai@didim365.co.kr
Requires-Python: >=3.8.1,<4.0
Classifier: License :: Other/Proprietary License
Classifier: Programming Language :: Python :: 3
Classifier: Programming Language :: Python :: 3.9
Classifier: Programming Language :: Python :: 3.10
Classifier: Programming Language :: Python :: 3.11
Classifier: Programming Language :: Python :: 3.12
Requires-Dist: aiohttp (>=3.10.1,<4.0.0)
Requires-Dist: langchain (>=0.2.0)
Requires-Dist: langchain-community (>=0.2.0)
Requires-Dist: langchain-core (>=0.2.1)
Requires-Dist: langchain-text-splitters (>=0.2.0)
Requires-Dist: pyhcx (>=0.9.8)
Project-URL: Repository, https://gitlab.com/didim365-ai/naver-ai
Project-URL: Source Code, https://gitlab-ai.didim365.com/didim365/naverai/langchain_hcxai/
